regugcb/__init__.py
regugcb-0.4.dist-info/METADATA
regugcb-0.4.dist-info/WHEEL
regugcb-0.4.dist-info/top_level.txt
regugcb-0.4.dist-info/RECORD
