Metadata-Version: 2.1
Name: regugcb
Version: 0.4
Summary: Functions for Regulation GCB
Home-page: https://catalyseur.ca/
Author: Francis B. Lavoie
Author-email: francis.b.lavoie@usherbrooke.ca
License: UNKNOWN
Platform: UNKNOWN
Classifier: Programming Language :: Python :: 3
Classifier: License :: OSI Approved :: BSD License
Classifier: Operating System :: OS Independent
